pysoilmap/__init__.py
pysoilmap/__main__.py
pysoilmap/shapeops.py
pysoilmap/cli/__init__.py
pysoilmap/cli/help.py
pysoilmap/cli/shapefile.py
pysoilmap-0.1.0.dist-info/METADATA
pysoilmap-0.1.0.dist-info/WHEEL
pysoilmap-0.1.0.dist-info/entry_points.txt
pysoilmap-0.1.0.dist-info/top_level.txt
pysoilmap-0.1.0.dist-info/zip-safe
pysoilmap-0.1.0.dist-info/RECORD
