Metadata-Version: 2.1
Name: pysoilmap
Version: 0.1.0
Summary: Tools for performing Digital Soil Mapping (DSM) with python.
Home-page: https://github.com/pysoilmap/pysoilmap
Author: Thomas Gläßle
Author-email: thomas@coldfix.de
License: UNKNOWN
Keywords: DSM,GIS,soil,topography,machine learning,kriging
Platform: UNKNOWN
Classifier: Development Status :: 1 - Planning
Classifier: Programming Language :: Python :: 3
Classifier: Topic :: Scientific/Engineering :: GIS
Requires-Python: >=3.7
Requires-Dist: click
Requires-Dist: geopandas
Requires-Dist: pygeos
Requires-Dist: shapely
Provides-Extra: dev
Requires-Dist: flake8 ; extra == 'dev'
Requires-Dist: pytest ; extra == 'dev'
Requires-Dist: twine ; extra == 'dev'
Provides-Extra: doc
Requires-Dist: sphinx ; extra == 'doc'
Requires-Dist: sphinx-automodapi ; extra == 'doc'
Requires-Dist: sphinx-autodoc-typehints ; extra == 'doc'
Requires-Dist: sphinx-click ; extra == 'doc'
